MANIFEST.in
README.rst
requirements.txt
setup.py
bin/funniest-joke
docs/a.txt
docs/b.txt
funniest_noga/__init__.py
funniest_noga/data.json
funniest_noga/text.py
funniest_noga.egg-info/PKG-INFO
funniest_noga.egg-info/SOURCES.txt
funniest_noga.egg-info/dependency_links.txt
funniest_noga.egg-info/not-zip-safe
funniest_noga.egg-info/requires.txt
funniest_noga.egg-info/top_level.txt