Metadata-Version: 1.1
Name: funniest-noga
Version: 0.1
Summary: The funniest_noga joke in the world
Home-page: http://github.com/storborg/funniest_noga
Author: Flying Circus
Author-email: flyingcircus@example.com
License: MIT
Keywords: funniest_noga joke comedy flying circus
Platform: UNKNOWN
Classifier: Development Status :: 3 - Alpha
Classifier: License :: OSI Approved :: MIT License
Classifier: Programming Language :: Python :: 2.7
Classifier: Topic :: Text Processing :: Linguistic
